fastmicro/__init__.py
fastmicro/entrypoint.py
fastmicro/env.py
fastmicro/messaging/__init__.py
fastmicro/messaging/header.py
fastmicro/messaging/kafka.py
fastmicro/messaging/memory.py
fastmicro/messaging/redis.py
fastmicro/messaging/topic.py
fastmicro/py.typed
fastmicro/serializer/__init__.py
fastmicro/serializer/json.py
fastmicro/serializer/msgpack.py
fastmicro/service.py
fastmicro-0.3.2.dist-info/WHEEL
fastmicro-0.3.2.dist-info/METADATA
fastmicro-0.3.2.dist-info/RECORD
