Metadata-Version: 2.1
Name: fastmicro
Version: 0.3.2
Summary: Fast, simple microservice framework
Home-page: https://github.com/larmoreg/fastmicro
License: MIT
Keywords: fast,simple,microservice,framework,asyncio,redis,kafka
Author: larmoreg
Author-email: larmoreg@gmail.com
Requires-Python: >=3.7,<3.11
Classifier: Development Status :: 3 - Alpha
Classifier: Framework :: AsyncIO
Classifier: Intended Audience :: Developers
Classifier: License :: OSI Approved :: MIT License
Classifier: Natural Language :: English
Classifier: Operating System :: POSIX
Classifier: Operating System :: POSIX :: Linux
Classifier: Programming Language :: Python
Classifier: Programming Language :: Python :: 3
Classifier: Programming Language :: Python :: 3 :: Only
Classifier: Programming Language :: Python :: 3.7
Classifier: Programming Language :: Python :: 3.8
Classifier: Programming Language :: Python :: 3.9
Classifier: Programming Language :: Python :: Implementation :: CPython
Classifier: Programming Language :: Python :: Implementation :: PyPy
Classifier: Topic :: System :: Distributed Computing
Classifier: Topic :: System :: Networking
Provides-Extra: kafka
Provides-Extra: msgpack
Provides-Extra: redis
Requires-Dist: aiokafka (>=0.7.2,<0.8.0); extra == "kafka"
Requires-Dist: aioredis (>=2.0.1,<3.0.0); extra == "redis"
Requires-Dist: msgpack (>=1.0.3,<2.0.0); extra == "msgpack"
Requires-Dist: pydantic (>=1.8.2,<2.0.0)
Requires-Dist: uvloop (>=0.15.3,<0.16.0)
Project-URL: Repository, https://github.com/larmoreg/fastmicro
